{
  "id": "client_grid",
  "type": "SharedSlice",
  "name": "ClientGrid",
  "description": "ClientGrid",
  "variations": [
    {
      "id": "default",
      "name": "Default",
      "docURL": "...",
      "version": "sktwi1xtmkfgx8626",
      "description": "ClientGrid",
      "primary": {},
      "items": {
        "client_logo": {
          "type": "Image",
          "config": {
            "label": "Client Logo",
            "constraint": {},
            "thumbnails": []
          }
        }
      },
      "imageUrl": "https://images.prismic.io/slice-machine/621a5ec4-0387-4bc5-9860-2dd46cbc07cd_default_ss.png?auto=compress,format"
    }
  ]
}